basecampui/__init__.py
basecampui/_modidx.py
basecampui/all.py
basecampui/chat.py
basecampui/common.py
basecampui/interactive.py
basecampui/markdown.py
basecampui/utils.py
basecampui-0.0.1.dist-info/licenses/LICENSE
basecampui-0.0.1.dist-info/METADATA
basecampui-0.0.1.dist-info/WHEEL
basecampui-0.0.1.dist-info/entry_points.txt
basecampui-0.0.1.dist-info/top_level.txt
basecampui-0.0.1.dist-info/RECORD
