Metadata-Version: 2.4
Name: basecampui
Version: 0.0.1
Summary: A FastHTML UI component library based on basecoat CSS
Home-page: https://github.com/taya-nicholas/basecampui
Author: Taya Nicholas
Author-email: taya.nicholas@outlook.com
License: Apache Software License 2.0
Keywords: nbdev jupyter notebook python
Classifier: Development Status :: 4 - Beta
Classifier: Intended Audience :: Developers
Classifier: Natural Language :: English
Classifier: Programming Language :: Python :: 3.9
Classifier: Programming Language :: Python :: 3.10
Classifier: Programming Language :: Python :: 3.11
Classifier: Programming Language :: Python :: 3.12
Classifier: License :: OSI Approved :: Apache Software License
Requires-Python: >=3.9
License-File: LICENSE
Requires-Dist: fastcore
Requires-Dist: python-fasthtml
Requires-Dist: fastlucide
Provides-Extra: dev
Requires-Dist: lancedb; extra == "dev"
Requires-Dist: google-genai; extra == "dev"
Requires-Dist: lisette; extra == "dev"
Dynamic: author
Dynamic: author-email
Dynamic: classifier
Dynamic: description
Dynamic: description-content-type
Dynamic: home-page
Dynamic: keywords
Dynamic: license
Dynamic: license-file
Dynamic: provides-extra
Dynamic: requires-dist
Dynamic: requires-python
Dynamic: summary
